{
  "fsdfsdf": "fsdfsdf",
  "toggle": "toggle",
  "Валюта": "Валюта",
  "Возраст": "Возраст",
  "Войти": "Войти",
  "Выйти": "Выйти",
  "Главная": "Главная",
  "Город": "Город",
  "Загрузка": "Загрузка",
  "Закрыть": "Закрыть",
  "Имя": "Имя",
  "Логин": "Логин",
  "Неверный логин или пароль": "Неверный логин или пароль",
  "О сайте": "О сайте",
  "Обновить страницу": "Обновить страницу",
  "Открыть": "Открыть",
  "Отменить": "Отменить",
  "Поробуйте обновить страницу": "Поробуйте обновить страницу",
  "Произошла непредвиденная ошибка": "Произошла непредвиденная ошибка",
  "Произошла ошибка при загрузке профиля": "Произошла ошибка при загрузке профиля",
  "Профиль": "Профиль",
  "Редактировать": "Редактировать",
  "Сохранить": "Сохранить",
  "Ссылка на аватар": "Ссылка на аватар",
  "Страна": "Страна",
  "Страница не найдена": "Страница не найдена",
  "Увеличить": "Увеличить",
  "Уменьшить": "Уменьшить",
  "Фамилия": "Фамилия"
}
